rcut/__init__.py
rcut/rcut.py
rcut-0.0.1.dist-info/METADATA
rcut-0.0.1.dist-info/WHEEL
rcut-0.0.1.dist-info/entry_points.txt
rcut-0.0.1.dist-info/top_level.txt
rcut-0.0.1.dist-info/RECORD
