Metadata-Version: 2.1
Name: rcut
Version: 0.0.1
Summary: python version of rcut
Author-email: Haoxi Tan <haoxi.tan@gmail.com>
Project-URL: Homepage, https://github.com/h4sh5/rcut.py
Project-URL: Issues, https://github.com/h4sh5/rcut.py/issues
Requires-Python: >=3.8
